SnowMapPy/__init__.py
SnowMapPy/cloud/__init__.py
SnowMapPy/cloud/auth.py
SnowMapPy/cloud/loader.py
SnowMapPy/cloud/processor.py
SnowMapPy/core/__init__.py
SnowMapPy/core/data_io.py
SnowMapPy/core/quality.py
SnowMapPy/core/spatial.py
SnowMapPy/core/temporal.py
SnowMapPy/core/utils.py
SnowMapPy/local/__init__.py
SnowMapPy/local/file_handler.py
SnowMapPy/local/preparator.py
SnowMapPy/local/processor.py
SnowMapPy/tests/__init__.py
SnowMapPy/tests/test_cloud/__init__.py
SnowMapPy/tests/test_cloud/real_cloud_test.py
SnowMapPy/tests/test_cloud/test_basic_cloud.py
SnowMapPy/tests/test_core/__init__.py
SnowMapPy/tests/test_core/test_quality.py
SnowMapPy/tests/test_local/__init__.py
snowmappy-1.0.5.dist-info/licenses/LICENSE
snowmappy-1.0.5.dist-info/METADATA
snowmappy-1.0.5.dist-info/WHEEL
snowmappy-1.0.5.dist-info/top_level.txt
snowmappy-1.0.5.dist-info/RECORD
