Metadata-Version: 2.4
Name: SnowMapPy
Version: 1.0.5
Summary: A comprehensive Python package for processing MODIS NDSI data from local files and Google Earth Engine
Home-page: https://github.com/haytamelyo/SnowMapPy
Author: Haytam Elyoussfi, Hatim BECHRI
Author-email: Haytam Elyoussfi <haytam.elyoussfi@um6p.ma>, Hatim BECHRI <hatim.bechri@usms.ac.ma>
License: MIT
Project-URL: Bug Reports, https://github.com/haytamelyo/SnowMapPy/issues
Project-URL: Source, https://github.com/haytamelyo/SnowMapPy
Project-URL: Documentation, https://github.com/haytamelyo/SnowMapPy#readme
Keywords: modis,snow,remote sensing,earth engine,gis,hydrology
Classifier: Development Status :: 4 - Beta
Classifier: Intended Audience :: Science/Research
Classifier: License :: OSI Approved :: MIT License
Classifier: Operating System :: OS Independent
Classifier: Programming Language :: Python :: 3
Classifier: Programming Language :: Python :: 3.11
Classifier: Programming Language :: Python :: 3.12
Classifier: Topic :: Scientific/Engineering :: GIS
Classifier: Topic :: Scientific/Engineering :: Atmospheric Science
Requires-Python: >=3.11
License-File: LICENSE
Requires-Dist: numpy>=1.20.0
Requires-Dist: scipy>=1.7.0
Requires-Dist: pandas>=1.3.0
Requires-Dist: xarray>=0.19.0
Requires-Dist: rasterio>=1.2.0
Requires-Dist: rioxarray>=0.11.0
Requires-Dist: geopandas>=0.10.0
Requires-Dist: pyproj>=3.0.0
Requires-Dist: shapely>=1.8.0
Requires-Dist: earthengine-api>=0.1.0
Requires-Dist: zarr>=2.10.0
Requires-Dist: tqdm>=4.60.0
Requires-Dist: joblib>=1.0.0
Provides-Extra: dev
Requires-Dist: pytest>=6.0; extra == "dev"
Requires-Dist: flake8>=3.8; extra == "dev"
Requires-Dist: black>=21.0; extra == "dev"
Requires-Dist: matplotlib>=3.5.0; extra == "dev"
Dynamic: author
Dynamic: home-page
Dynamic: license-file
Dynamic: requires-python
